mota/__init__.py
mota/core.py
mota/custom_anthropic.py
mota/custom_groq.py
mota/custom_interface.py
mota/loader.py
mota/main.py
mota/seek.py
mota-0.1.1.dist-info/licenses/LICENSE
mota-0.1.1.dist-info/licenses/NOTICE
mota-0.1.1.dist-info/METADATA
mota-0.1.1.dist-info/WHEEL
mota-0.1.1.dist-info/entry_points.txt
mota-0.1.1.dist-info/top_level.txt
mota-0.1.1.dist-info/RECORD
