Metadata-Version: 2.4
Name: mota
Version: 0.1.1
Summary: A Comprehensive LLM API Interaction Tool
Author-email: KEJIA <DETONG.KEJI@GMAIL.COM>
License: GPL-3.0-or-later
Project-URL: Repository, https://codeberg.org/wizardelf/mota
Project-URL: Documentation, https://codeberg.org/wizardelf/mota/src/branch/ling/README.md
Keywords: AI,LLM
Classifier: Development Status :: 5 - Production/Stable
Classifier: Topic :: Scientific/Engineering :: Artificial Intelligence
Classifier: Intended Audience :: Science/Research
Classifier: Programming Language :: Python :: 3
Classifier: Programming Language :: Python :: 3.8
Classifier: Programming Language :: Python :: 3.9
Classifier: Programming Language :: Python :: 3.10
Classifier: Programming Language :: Python :: 3.11
Classifier: Programming Language :: Python :: 3.12
Classifier: Topic :: Software Development :: Libraries :: Python Modules
Requires-Python: >=3.8
License-File: LICENSE
License-File: NOTICE
Requires-Dist: typer~=0.15.1
Requires-Dist: typing-extensions~=4.12.2
Requires-Dist: edn-format~=0.7.5
Requires-Dist: requests~=2.32.3
Requires-Dist: python-dotenv~=1.0.1
Requires-Dist: anthropic>=0.47.2
Requires-Dist: google-generativeai>=0.8.4
Requires-Dist: mistralai>=1.5.0
Requires-Dist: openai>=1.64.0
Requires-Dist: pydantic~=2.10.6
Requires-Dist: keyring~=25.6.0
Requires-Dist: python-gnupg~=0.5.4
Requires-Dist: groq>=0.18.0
Requires-Dist: langchain>=0.3.20
Requires-Dist: langchain-community>=0.3.19
Requires-Dist: langchain-huggingface>=0.1.2
Requires-Dist: faiss-cpu>=1.10.0
Requires-Dist: sentence-transformers>=3.4.1
Provides-Extra: test
Requires-Dist: pytest~=8.3.4; extra == "test"
Requires-Dist: pytest-cov~=6.0.0; extra == "test"
Requires-Dist: mock~=5.1.0; extra == "test"
Dynamic: license-file
